{
  "type": "samurai_armory:jap_furnace_recipe",
  "ingredient1": {
    "item": "minecraft:iron_ingot"
  },
  "ingredient2": {
    "item": "minecraft:iron_ingot"
  },
  "ingredient3": {
    "item": "minecraft:gold_ingot"
  },
  "tool1": {
    "tag": "samurai_armory:sa_blacksmith_hammer"
  },
  "tool2": {
    "tag": "samurai_armory:sa_blacksmith_tongs"
  },
  "tool3": {
    "tag": "samurai_armory:sa_blacksmith_bellows"
  },
  "experience": 10,
  "cooking_time":800,

  "result": {
    "item": "samurai_armory:black_katana"
  }
}